nested_diff/__init__.py
nested_diff/cli.py
nested_diff/diff_tool.py
nested_diff/formatters.py
nested_diff/handlers.py
nested_diff/patch_tool.py
nested_diff-1.9.0.dist-info/entry_points.txt
nested_diff-1.9.0.dist-info/licenses/LICENSE
nested_diff-1.9.0.dist-info/WHEEL
nested_diff-1.9.0.dist-info/METADATA
nested_diff-1.9.0.dist-info/RECORD
