Metadata-Version: 2.4
Name: nested_diff
Version: 1.9.0
Summary: Recursive diff and patch for nested structures.
Keywords: diff,nested-diff,recursive-diff,nested-data,data-structures
Author-email: Michael Samoglyadov <mixas.sr@gmail.com>
Requires-Python: >=3.7
Classifier: Development Status :: 5 - Production/Stable
Classifier: Intended Audience :: Developers
Classifier: Intended Audience :: Information Technology
Classifier: Intended Audience :: System Administrators
Classifier: License :: OSI Approved :: Apache Software License
Classifier: Operating System :: OS Independent
Classifier: Programming Language :: Python
Classifier: Programming Language :: Python :: 3
Classifier: Programming Language :: Python :: 3 :: Only
Classifier: Programming Language :: Python :: 3.7
Classifier: Programming Language :: Python :: 3.8
Classifier: Programming Language :: Python :: 3.9
Classifier: Programming Language :: Python :: 3.10
Classifier: Programming Language :: Python :: 3.11
Classifier: Programming Language :: Python :: 3.12
Classifier: Programming Language :: Python :: 3.13
Classifier: Programming Language :: Python :: 3.14
Classifier: Programming Language :: Python :: Implementation :: CPython
Classifier: Programming Language :: Python :: Implementation :: PyPy
Classifier: Topic :: File Formats :: JSON
Classifier: Topic :: Software Development :: Quality Assurance
Classifier: Topic :: Software Development :: Testing
Classifier: Topic :: System :: Systems Administration
Classifier: Topic :: Utilities
License-File: LICENSE
Requires-Dist: pyyaml >= 5.3 ; extra == "cli"
Requires-Dist: tomli >= 1.1.0  ; extra == "cli" and ( python_version < "3.11")
Requires-Dist: tomli-w >= 1.0.0 ; extra == "cli"
Requires-Dist: darglint ; extra == "lint"
Requires-Dist: pytest ; extra == "test"
Requires-Dist: pytest-cov ; extra == "test"
Requires-Dist: pytest-ruff ; extra == "test"
Requires-Dist: ruff==0.14.8 ; extra == "test"
Project-URL: Homepage, https://github.com/mr-mixas/Nested-Diff.py
Project-URL: Repository, https://github.com/mr-mixas/Nested-Diff.py.git
Provides-Extra: cli
Provides-Extra: lint
Provides-Extra: test
